healpix_c.cpython-38-x86_64-linux-gnu.so
sfd_c.cpython-38-x86_64-linux-gnu.so
mwdust/Combined15.py
mwdust/Combined19.py
mwdust/Drimmel03.py
mwdust/DustMap3D.py
mwdust/Green15.py
mwdust/Green17.py
mwdust/Green19.py
mwdust/HierarchicalHealpixMap.py
mwdust/Marshall06.py
mwdust/SFD.py
mwdust/Sale14.py
mwdust/Zero.py
mwdust/Zucker25.py
mwdust/__init__.py
mwdust/util/__init__.py
mwdust/util/combine_dustmaps19.py
mwdust/util/download.py
mwdust/util/extCurves.py
mwdust/util/fortranfile.py
mwdust/util/healpix.py
mwdust/util/read_Drimmel.py
mwdust/util/read_SFD.py
mwdust/util/tools.py
mwdust/util/extCurves/apj398709t6_ascii.txt
mwdust/util/extCurves/extinction.tbl
mwdust-1.7.dist-info/AUTHORS.txt
mwdust-1.7.dist-info/LICENSE
mwdust-1.7.dist-info/METADATA
mwdust-1.7.dist-info/WHEEL
mwdust-1.7.dist-info/top_level.txt
mwdust-1.7.dist-info/RECORD
