Metadata-Version: 2.1
Name: mwdust
Version: 1.7
Summary: Dust in the Milky Way
Home-page: https://github.com/jobovy/mwdust
Author: Jo Bovy
Author-email: bovy@astro.utoronto.ca
License: New BSD
Classifier: Development Status :: 6 - Mature
Classifier: Intended Audience :: Science/Research
Classifier: License :: OSI Approved :: BSD License
Classifier: Operating System :: OS Independent
Classifier: Programming Language :: C
Classifier: Programming Language :: Python :: 3
Classifier: Topic :: Scientific/Engineering :: Astronomy
Classifier: Topic :: Scientific/Engineering :: Physics
License-File: LICENSE
License-File: AUTHORS.txt
Requires-Dist: numpy
Requires-Dist: scipy
Requires-Dist: matplotlib
Requires-Dist: astropy
Requires-Dist: h5py
Requires-Dist: tqdm
Requires-Dist: requests
Requires-Dist: healpy
